LICENSE.txt
MANIFEST.in
Makefile
README.rst
ez_setup.py
install-gcam.py
requirements.in
setup.cfg
setup.py
version.sh
docs/Makefile
docs/make.bat
docs/source/api.rst
docs/source/conditional-xml.rst
docs/source/conf.py
docs/source/config.rst
docs/source/gcamtool.rst
docs/source/gui.rst
docs/source/index.rst
docs/source/initialize.rst
docs/source/install.rst
docs/source/intro.rst
docs/source/landProtection-xml.rst
docs/source/pic.rst
docs/source/project-xml.rst
docs/source/pygcam.XMLFile.rst
docs/source/pygcam.carbonTax.rst
docs/source/pygcam.chart.rst
docs/source/pygcam.config.rst
docs/source/pygcam.diff.rst
docs/source/pygcam.error.rst
docs/source/pygcam.gcam.rst
docs/source/pygcam.landProtection.rst
docs/source/pygcam.log.rst
docs/source/pygcam.project.rst
docs/source/pygcam.query.rst
docs/source/pygcam.scenarioSetup.rst
docs/source/pygcam.subcommand.rst
docs/source/pygcam.units.rst
docs/source/pygcam.utils.rst
docs/source/pygcam.xmlEditor.rst
docs/source/query-xml.rst
docs/source/resPolicy-xml.rst
docs/source/rewrites-xml.rst
docs/source/scenarios-xml.rst
docs/source/setup.rst
docs/source/terminology.rst
docs/source/tutorial.rst
docs/source/tutorial1.rst
docs/source/tutorial2.rst
docs/source/tutorial3.rst
docs/source/tutorial4.rst
docs/source/xmlFiles.rst
docs/source/_static/lineno_fix.css
docs/source/_static/theme_overrides.css
docs/source/images/Climate_forcing-tax-10-0-base-0.png
docs/source/images/ConfigVarStructure.jpg
docs/source/images/Global_mean_temperature-tax-10-0-base-0.png
docs/source/images/Land_Allocation-tax-10-0-base-0-by-region-2050.png
docs/source/images/Refined-liquids-production-by-technology-base-0-mod.png
docs/source/images/Refined-liquids-production-by-technology-base-0-unstacked.png
docs/source/images/Refined-liquids-production-by-technology-base-0.png
docs/source/images/Refined-liquids-production-by-technology-tax-10-0-base-0-USA.png
docs/source/images/Refined-liquids-production-by-technology-tax-10-0-base-0.png
pygcam.egg-info/PKG-INFO
pygcam.egg-info/SOURCES.txt
pygcam.egg-info/dependency_links.txt
pygcam.egg-info/entry_points.txt
pygcam.egg-info/pbr.json
pygcam.egg-info/requires.txt
pygcam.egg-info/top_level.txt
pygcam.egg-info/zip-safe
