Metadata-Version: 1.1
Name: pygcam
Version: 1.11.1
Summary: Python (2 and 3) library and scripts for interfacing with GCAM
Home-page: https://github.com/JGCRI/pygcam
Author: Richard Plevin
Author-email: rich@plevin.com
License: MIT License
Download-URL: https://github.com/JGCRI/pygcam.git
Platform: Windows
Platform: MacOS
Platform: Linux
Classifier: Development Status :: 5 - Production/Stable
Classifier: License :: OSI Approved :: MIT License
Classifier: Intended Audience :: Science/Research
